metadata_to_db/__init__.py
metadata_to_db/configHandler.py
metadata_to_db/databaseHandler.py
metadata_to_db/dicomToDb.py
metadata_to_db/metaToDbConfigHandler.py
metadata_to_db/niftiToDb.py
metadata_to_db-0.0.8.dist-info/METADATA
metadata_to_db-0.0.8.dist-info/WHEEL
metadata_to_db-0.0.8.dist-info/top_level.txt
metadata_to_db-0.0.8.dist-info/RECORD
