Metadata-Version: 2.1
Name: metadata-to-db
Version: 0.0.8
Summary: Library for storing image metadata from a directory of images to a PostgreSQL DB.
Home-page: https://github.com/Matt-Conrad/DicomToDatabase
Author: Matt-Conrad
Author-email: mattgrayconrad@gmail.com
License: UNKNOWN
Platform: UNKNOWN
Classifier: Programming Language :: Python :: 3.6
Classifier: Operating System :: OS Independent
Requires-Python: >=3.6
